{
    "fluentMethods": true,
    "relationships": [],
    "fields": [
        {
            "fieldName": "primeiroNome",
            "fieldType": "String",
            "fieldValidateRules": [
                "required"
            ]
        },
        {
            "fieldName": "ultimoNome",
            "fieldType": "String",
            "fieldValidateRules": [
                "required"
            ]
        },
        {
            "fieldName": "especialidade",
            "fieldType": "String",
            "fieldValidateRules": [
                "required"
            ]
        },
        {
            "fieldName": "email",
            "fieldType": "String",
            "fieldValidateRules": [
                "required"
            ]
        },
        {
            "fieldName": "ativo",
            "fieldType": "Boolean",
            "fieldValidateRules": [
                "required"
            ]
        },
        {
            "fieldName": "status",
            "fieldType": "StatusMedicoEnum",
            "fieldValues": "OCUPADO,DISPONIVEL",
            "fieldValidateRules": [
                "required"
            ]
        },
        {
            "fieldName": "cidade",
            "fieldType": "String"
        },
        {
            "fieldName": "estado",
            "fieldType": "String"
        }
    ],
    "changelogDate": "20180302131226",
    "javadoc": "Generated by JHipster IDE plugin",
    "entityTableName": "medico",
    "dto": "mapstruct",
    "pagination": "infinite-scroll",
    "service": "serviceImpl",
    "jpaMetamodelFiltering": false,
    "angularJSSuffix": "mySuffix"
}